mcp23017/__init__.py
mcp23017/i2c.py
mcp23017/mcp23017.py
mcp23017-1.1.0.dist-info/METADATA
mcp23017-1.1.0.dist-info/WHEEL
mcp23017-1.1.0.dist-info/top_level.txt
mcp23017-1.1.0.dist-info/RECORD
