Metadata-Version: 2.1
Name: mcp23017
Version: 1.1.0
Summary: MCP23017 Library
Home-page: https://github.com/open-thngs/MCP23017-python
Author: Mirko Haeberlin
Author-email: mirko.haeberlin@open-things.de
Classifier: Programming Language :: Python :: 3
Classifier: License :: OSI Approved :: MIT License
Classifier: Operating System :: OS Independent
Requires-Python: >=3.6
